word_latex_mcp/__init__.py
word_latex_mcp/backup.py
word_latex_mcp/converter.py
word_latex_mcp/file_manager.py
word_latex_mcp/models.py
word_latex_mcp/policy.py
word_latex_mcp/reporter.py
word_latex_mcp/scanner.py
word_latex_mcp/server.py
word_latex_mcp/handlers/__init__.py
word_latex_mcp/handlers/cases_handler.py
word_latex_mcp/handlers/matrix_handler.py
word_latex_mcp-0.4.1.dist-info/METADATA
word_latex_mcp-0.4.1.dist-info/WHEEL
word_latex_mcp-0.4.1.dist-info/entry_points.txt
word_latex_mcp-0.4.1.dist-info/licenses/LICENSE
word_latex_mcp-0.4.1.dist-info/RECORD
