Metadata-Version: 2.4
Name: word-latex-mcp
Version: 0.4.1
Summary: MCP tool to convert LaTeX in Word documents to native equations
Project-URL: Homepage, https://github.com/word-latex-mcp/word-latex-mcp
Project-URL: Repository, https://github.com/word-latex-mcp/word-latex-mcp
Project-URL: Documentation, https://github.com/word-latex-mcp/word-latex-mcp#readme
Project-URL: Bug Tracker, https://github.com/word-latex-mcp/word-latex-mcp/issues
Author: Word LaTeX MCP Contributors
License: MIT
License-File: LICENSE
Keywords: claude,cursor,equation,formula,latex,math,mcp,microsoft-word,omml,word
Classifier: Development Status :: 4 - Beta
Classifier: Environment :: Win32 (MS Windows)
Classifier: Intended Audience :: End Users/Desktop
Classifier: Intended Audience :: Science/Research
Classifier: License :: OSI Approved :: MIT License
Classifier: Operating System :: Microsoft :: Windows
Classifier: Programming Language :: Python :: 3
Classifier: Programming Language :: Python :: 3.10
Classifier: Programming Language :: Python :: 3.11
Classifier: Programming Language :: Python :: 3.12
Classifier: Topic :: Office/Business :: Office Suites
Classifier: Topic :: Scientific/Engineering
Classifier: Topic :: Text Processing :: Markup :: LaTeX
Requires-Python: >=3.10
Requires-Dist: mcp>=1.0.0
Requires-Dist: pywin32>=306
